{
  "name": "bgn",
  "groups": [
    {
      "description": "Личные местоимения",
      "questions": [
        {"text": "аз", "answers": ["я"]},
        {"text": "ти", "answers": ["ты"]},
        {"text": "той", "answers": ["он"]},
        {"text": "тя", "answers": ["она"]},
        {"text": "то", "answers": ["оно"]},
        {"text": "ние", "answers": ["мы"]},
        {"text": "вие", "answers": ["вы"]},
        {"text": "те", "answers": ["они"]}
      ]
    },
    {
      "description": "Указательные местоимения",
      "questions": [
        {"text":  "този", "answers":  ["этот"]},
        {"text":  "тази", "answers":  ["эта"]},
        {"text":  "това", "answers":  ["это"]},
        {"text":  "тези", "answers":  ["эти"]},
        {"text":  "онзи", "answers":  ["тот"]},
        {"text":  "онази", "answers":  ["та"]},
        {"text":  "онова", "answers":  ["то"]},
        {"text":  "онези", "answers":  ["те"]}
      ]
    },
    {
      "description": "Глагол-связка съм (есть)",
      "questions": [
        {"text": "е", "answers": ["той", "тя", "то"]},
        {"text": "са", "answers": ["те"]},
        {"text": "си", "answers": ["ти"]},
        {"text": "сте", "answers": ["вие"]},
        {"text": "съм", "answers": ["аз"]},
        {"text": "сме", "answers": ["ние"]}
      ]
    },
    {
      "description": "Наречия времени",
      "questions": [
        {"text": "днес", "answers": ["сегодня"]},
        {"text": "утре", "answers": ["завтра"]},
        {"text": "(в)другиден", "answers": ["послезавтра"]},
        {"text": "вчера", "answers": ["вчера"]},

        {"text": "позавчера", "answers": ["завчера", "оня ден"]},

        {"text": "сутрин", "answers": ["по утрам"]},
        {"text": "сутринта", "answers": ["этим утром"]},
        {"text": "вечер", "answers": ["по вечерам"]},
        {"text": "вечерта", "answers": ["этим вечером"]},
        {"text": "довечера", "answers": ["сегодня вечером"]},
        {"text": "снощи", "answers": ["вчера вечером"]},
        {"text": "сега", "answers": ["сейчас"]},
        {"text": "вече", "answers": ["уже"]},
        {"text": "още", "answers": ["ещё"]},
        {"text": "винаги", "answers": ["всегда"]},
        {"text": "обикновено", "answers": ["обычно"]},
        {"text": "редовно", "answers": ["регулярно"]},
        {"text": "често", "answers": ["часто"]},
        {"text": "понякога", "answers": ["иногда"]},
        {"text": "от време на време", "answers": ["время от времени"]},
        {"text": "рядкр", "answers": ["редко"]},
        {"text": "много рядко", "answers": ["очень редко"]},
        {"text": "почти никога", "answers": ["почти никогда"]},
        {"text": "никога не", "answers": ["никогда не"]}
      ]
    },
    {
      "description": "Вопросительные слова",
      "questions": [
        {"text": "какво", "answers": ["что"]},
        {"text": "къде", "answers": ["где"]},
        {"text": "откыде", "answers": ["откуда"]},
        {"text": "кога", "answers": ["когда"]},
        {"text": "защо", "answers": ["почему"]},
        {"text": "колко", "answers": ["сколько"]},

        {"text": "кой", "answers": ["кто (общ, из многих, м.р.)"]},
        {"text": "коя", "answers": ["кто (общ, из многих, ж.р.)"]},
        {"text": "кое", "answers": ["кто (общ, из многих, ср.р.)"]},
        {"text": "кои", "answers": ["кто (общ, из многих, мн.ч.)"]},
        {"text": "какъв", "answers": ["кто (по профессии и национальности, качество предмета, м.р.)"]},
        {"text": "каква", "answers": ["кто (по профессии и национальности, качество предмета, ж.р.)"]},
        {"text": "какво", "answers": ["кто (по профессии и национальности, качество предмета, ср.р.)"]},
        {"text": "какви", "answers": ["кто (по профессии и национальности, качество предмета, мн.ч.)"]},

        {"text": "какой (восклицание)", "answers": ["какыв", "колко"]}
      ]
    }
  ]
}
